image_to_cpp/main.py
image_to_cpp-0.1.0.dist-info/entry_points.txt
image_to_cpp-0.1.0.dist-info/LICENSE
image_to_cpp-0.1.0.dist-info/WHEEL
image_to_cpp-0.1.0.dist-info/METADATA
image_to_cpp-0.1.0.dist-info/RECORD
