Metadata-Version: 2.1
Name: image-to-cpp
Version: 0.1.0
Summary: Convert an image into a c++ header file containing a bytes array. Useful for electronic projects using a thermal printer or a LCD display.
Home-page: https://framagit.org/roipoussiere/image-to-cpp
License: MIT
Keywords: image,thermal-printer,lcd,arduino,esp32
Author: Roipoussiere
Author-email: roipoussiere@protonmail.com
Requires-Python: >=3.9,<4.0
Classifier: License :: OSI Approved :: MIT License
Classifier: Programming Language :: Python :: 3
Classifier: Programming Language :: Python :: 3.10
Classifier: Programming Language :: Python :: 3.9
Requires-Dist: Pillow (>=9.1.1,<10.0.0)
Project-URL: Repository, https://framagit.org/roipoussiere/image-to-cpp.git
